[{"jessica.jones@alias.com":{"diiorio-iswc2015.html":"","ciancarini-eswc2014.html":""}},{"vanessa.ives@hell.com":{"groth-savesd2015.html":"","diiorio-iswc2015.html":"","bardi-savesd2015.html":""}},{"lyra.belacqua@ox.com":{"peroni-rashdoc2016.html":"","groth-savesd2015.html":""}},{"alice.liddell@whiterabbit.com":{"vahdati-savesd2016.html":""}},{"arthur.dent@fish.com":{"vahdati-savesd2016.html":"","diiorio-savesd2015.html":"","peroni-rashdoc2016.html":""}},{"arabella.strange@york.com":{"diiorio-www2016.html":"","kuhn-savesd2015.html":"","diiorio-savesd2015.html":"","bardi-savesd2015.html":""}},{"john.constantine@hell.com":{"diiorio-www2016.html":"","diiorio-savesd2015.html":"","ciancarini-eswc2014.html":""}},{"angelo.diiorio@unibo.it":{"wade-savesd2016.html":"rejected"}},{"silvio.peroni@unibo.it":{"wade-savesd2016.html":"accepted","kuhn-savesd2015.html":"accepted"}}]